mwt/__init__.py
mwt-0.9.2.dist-info/DESCRIPTION.rst
mwt-0.9.2.dist-info/METADATA
mwt-0.9.2.dist-info/RECORD
mwt-0.9.2.dist-info/WHEEL
mwt-0.9.2.dist-info/metadata.json
mwt-0.9.2.dist-info/top_level.txt
