Metadata-Version: 2.0
Name: mwt
Version: 0.9.2
Summary: Memoize with timeout
Home-page: https://github.com/ak15199/mwt.git
Author: Alex King
Author-email: alex_w_king@yahoo.com
License: MIT
Keywords: memoize cache python function decorator
Platform: UNKNOWN
Classifier: Development Status :: 5 - Production/Stable
Classifier: Intended Audience :: Developers
Classifier: Topic :: Software Development :: Libraries :: Python Modules
Classifier: Programming Language :: Python :: 2
Classifier: Programming Language :: Python :: 2.7
Classifier: Programming Language :: Python :: 3
Classifier: License :: OSI Approved :: BSD License
